{"_type":"export","__export_format":4,"__export_date":"2023-04-19T14:05:01.201Z","__export_source":"insomnia.desktop.app:v2023.1.0","resources":[{"_id":"req_b48caac4eeb345d9b082c9064546dafe","parentId":"fld_fb997989999b45a783a4568fe0ca6377","modified":1681903744551,"created":1681902894900,"url":"localhost:3000/vendas","name":"LISTAR","description":"","method":"GET","body":{},"parameters":[],"headers":[],"authentication":{},"metaSortKey":-1681902894900,"isPrivate":false,"settingStoreCookies":true,"settingSendCookies":true,"settingDisableRenderRequestBody":false,"settingEncodeUrl":true,"settingRebuildPath":true,"settingFollowRedirects":"global","_type":"request"},{"_id":"fld_fb997989999b45a783a4568fe0ca6377","parentId":"wrk_c14a89b946ed439791c1ebeb36f744c1","modified":1681902853500,"created":1681902853500,"name":"VENDAS","description":"","environment":{},"environmentPropertyOrder":null,"metaSortKey":-1681902853500,"_type":"request_group"},{"_id":"wrk_c14a89b946ed439791c1ebeb36f744c1","parentId":null,"modified":1681902842617,"created":1681902842617,"name":"Lojinha","description":"","scope":"collection","_type":"workspace"},{"_id":"req_3dd207dfe7f14e9c857e4972b14a82fb","parentId":"fld_fb997989999b45a783a4568fe0ca6377","modified":1681912905277,"created":1681902928207,"url":"localhost:3000/vendas/2","name":"LISTAR POR ID","description":"","method":"GET","body":{},"parameters":[],"headers":[],"authentication":{},"metaSortKey":-1681892254835.5,"isPrivate":false,"settingStoreCookies":true,"settingSendCookies":true,"settingDisableRenderRequestBody":false,"settingEncodeUrl":true,"settingRebuildPath":true,"settingFollowRedirects":"global","_type":"request"},{"_id":"req_aef0327aaa5147279d053ac4d5a3016b","parentId":"fld_fb997989999b45a783a4568fe0ca6377","modified":1681912552572,"created":1681912546658,"url":"localhost:3000/viewVendas","name":"VENDAS","description":"","method":"GET","body":{},"parameters":[],"headers":[],"authentication":{},"metaSortKey":-1681881614771,"isPrivate":false,"settingStoreCookies":true,"settingSendCookies":true,"settingDisableRenderRequestBody":false,"settingEncodeUrl":true,"settingRebuildPath":true,"settingFollowRedirects":"global","_type":"request"},{"_id":"req_cf2c4fcdf54a46e0926dcf24327ad7c7","parentId":"fld_fb997989999b45a783a4568fe0ca6377","modified":1681912786741,"created":1681912782104,"url":"localhost:3000/total","name":"TOTAL","description":"","method":"GET","body":{},"parameters":[],"headers":[],"authentication":{},"metaSortKey":-1681870974706.5,"isPrivate":false,"settingStoreCookies":true,"settingSendCookies":true,"settingDisableRenderRequestBody":false,"settingEncodeUrl":true,"settingRebuildPath":true,"settingFollowRedirects":"global","_type":"request"},{"_id":"req_cc4a770b30374719a093bdeff5b7829e","parentId":"fld_fb997989999b45a783a4568fe0ca6377","modified":1681905262541,"created":1681902940655,"url":"localhost:3000/venda","name":"CADASTRAR","description":"","method":"POST","body":{"mimeType":"application/json","text":"\t{\n\t\t\"quantidade\": 25,\n\t\t\"produtoId\": 1,\n\t\t\"vendedorId\": 1\n\t}"},"parameters":[],"headers":[{"name":"Content-Type","value":"application/json"}],"authentication":{},"metaSortKey":-1681775214126,"isPrivate":false,"settingStoreCookies":true,"settingSendCookies":true,"settingDisableRenderRequestBody":false,"settingEncodeUrl":true,"settingRebuildPath":true,"settingFollowRedirects":"global","_type":"request"},{"_id":"req_2b1c2ea614ed40a2b9d5caaa408b6426","parentId":"fld_fb997989999b45a783a4568fe0ca6377","modified":1681913060827,"created":1681902957080,"url":"localhost:3000/alterarVenda","name":"ALTERAR","description":"","method":"PUT","body":{"mimeType":"application/json","text":"\t{\n\t\t\"id\": 2,\n\t\t\"quantidade\": 20,\n\t\t\"produtoId\": 2,\n\t\t\"vendedorId\": 4\n\t}"},"parameters":[],"headers":[{"name":"Content-Type","value":"application/json"}],"authentication":{},"metaSortKey":-1681753933997,"isPrivate":false,"settingStoreCookies":true,"settingSendCookies":true,"settingDisableRenderRequestBody":false,"settingEncodeUrl":true,"settingRebuildPath":true,"settingFollowRedirects":"global","_type":"request"},{"_id":"req_9fb55719b28a4b2cac36041d7259b95d","parentId":"fld_fb997989999b45a783a4568fe0ca6377","modified":1681912925047,"created":1681902968406,"url":"localhost:3000/excluirVenda/1","name":"DELETAR","description":"","method":"DELETE","body":{"mimeType":"application/json","text":""},"parameters":[],"headers":[{"name":"Content-Type","value":"application/json"}],"authentication":{},"metaSortKey":-1681743293932.5,"isPrivate":false,"settingStoreCookies":true,"settingSendCookies":true,"settingDisableRenderRequestBody":false,"settingEncodeUrl":true,"settingRebuildPath":true,"settingFollowRedirects":"global","_type":"request"},{"_id":"req_bd6acc0b905b4604a2816895f4c4b867","parentId":"fld_331bd879dae34f6abf683c26e11c30c6","modified":1681904431786,"created":1681902985009,"url":"localhost:3000/produtos","name":"LISTAR","description":"","method":"GET","body":{},"parameters":[],"headers":[],"authentication":{},"metaSortKey":-1681902894900,"isPrivate":false,"settingStoreCookies":true,"settingSendCookies":true,"settingDisableRenderRequestBody":false,"settingEncodeUrl":true,"settingRebuildPath":true,"settingFollowRedirects":"global","_type":"request"},{"_id":"fld_331bd879dae34f6abf683c26e11c30c6","parentId":"wrk_c14a89b946ed439791c1ebeb36f744c1","modified":1681902999171,"created":1681902985006,"name":"PRODUTOS","description":"","environment":{},"environmentPropertyOrder":null,"metaSortKey":-1681794468546.25,"_type":"request_group"},{"_id":"req_91d211b213e044419157189f81f9b036","parentId":"fld_331bd879dae34f6abf683c26e11c30c6","modified":1681904442033,"created":1681902985013,"url":"localhost:3000/produtos/1","name":"LISTAR POR ID","description":"","method":"GET","body":{},"parameters":[],"headers":[],"authentication":{},"metaSortKey":-1681817774384,"isPrivate":false,"settingStoreCookies":true,"settingSendCookies":true,"settingDisableRenderRequestBody":false,"settingEncodeUrl":true,"settingRebuildPath":true,"settingFollowRedirects":"global","_type":"request"},{"_id":"req_a58742a5a42a40b3a866733c32cb1079","parentId":"fld_331bd879dae34f6abf683c26e11c30c6","modified":1681913037857,"created":1681902985017,"url":"localhost:3000/produto","name":"CADASTRAR","description":"","method":"POST","body":{"mimeType":"application/json","text":"\t{\n\t\t\"nome\": \"Nokia\",\n\t\t\"valor\": 29\n\t}"},"parameters":[],"headers":[{"name":"Content-Type","value":"application/json"}],"authentication":{},"metaSortKey":-1681775214126,"isPrivate":false,"settingStoreCookies":true,"settingSendCookies":true,"settingDisableRenderRequestBody":false,"settingEncodeUrl":true,"settingRebuildPath":true,"settingFollowRedirects":"global","_type":"request"},{"_id":"req_174347d1ba6e444b8243f3290d038275","parentId":"fld_331bd879dae34f6abf683c26e11c30c6","modified":1681913042813,"created":1681902985021,"url":"localhost:3000/alterarProduto","name":"ALTERAR","description":"","method":"PUT","body":{"mimeType":"application/json","text":"\t{\n\t\t\"id\": 2,\n\t\t\"nome\": \"Motorola\",\n\t\t\"valor\": 2211.11\n\t}"},"parameters":[],"headers":[{"name":"Content-Type","value":"application/json"}],"authentication":{},"metaSortKey":-1681753933997,"isPrivate":false,"settingStoreCookies":true,"settingSendCookies":true,"settingDisableRenderRequestBody":false,"settingEncodeUrl":true,"settingRebuildPath":true,"settingFollowRedirects":"global","_type":"request"},{"_id":"req_b8ba8f1950ba48e8ae8bbfa7e2f2a567","parentId":"fld_331bd879dae34f6abf683c26e11c30c6","modified":1681909710152,"created":1681902985025,"url":"localhost:3000/excluirProduto/3","name":"DELETAR","description":"","method":"DELETE","body":{},"parameters":[],"headers":[],"authentication":{},"metaSortKey":-1681743293932.5,"isPrivate":false,"settingStoreCookies":true,"settingSendCookies":true,"settingDisableRenderRequestBody":false,"settingEncodeUrl":true,"settingRebuildPath":true,"settingFollowRedirects":"global","_type":"request"},{"_id":"req_3ecc59dfdd134705bade617c2fb7bb38","parentId":"fld_5dd33b4bc38041d6820e9a61d2fb0a2f","modified":1681904559610,"created":1681903018584,"url":"localhost:3000/vendedores","name":"LISTAR","description":"","method":"GET","body":{},"parameters":[],"headers":[],"authentication":{},"metaSortKey":-1681902894900,"isPrivate":false,"settingStoreCookies":true,"settingSendCookies":true,"settingDisableRenderRequestBody":false,"settingEncodeUrl":true,"settingRebuildPath":true,"settingFollowRedirects":"global","_type":"request"},{"_id":"fld_5dd33b4bc38041d6820e9a61d2fb0a2f","parentId":"wrk_c14a89b946ed439791c1ebeb36f744c1","modified":1681903018582,"created":1681903018582,"name":"VENDEDORES","description":"","environment":{},"environmentPropertyOrder":null,"metaSortKey":-1681631891115.625,"_type":"request_group"},{"_id":"req_6531c35ae9a744f697bbc6e51847311c","parentId":"fld_5dd33b4bc38041d6820e9a61d2fb0a2f","modified":1681911478992,"created":1681908433469,"url":"localhost:3000/viewVendedor","name":"VIEW","description":"","method":"GET","body":{},"parameters":[],"headers":[],"authentication":{},"metaSortKey":-1681860334642,"isPrivate":false,"settingStoreCookies":true,"settingSendCookies":true,"settingDisableRenderRequestBody":false,"settingEncodeUrl":true,"settingRebuildPath":true,"settingFollowRedirects":"global","_type":"request"},{"_id":"req_3a31ec8e83f843fbab13571b0d69c30a","parentId":"fld_5dd33b4bc38041d6820e9a61d2fb0a2f","modified":1681904620317,"created":1681903018588,"url":"localhost:3000/vendedores/1","name":"LISTAR POR ID","description":"","method":"GET","body":{},"parameters":[],"headers":[],"authentication":{},"metaSortKey":-1681817774384,"isPrivate":false,"settingStoreCookies":true,"settingSendCookies":true,"settingDisableRenderRequestBody":false,"settingEncodeUrl":true,"settingRebuildPath":true,"settingFollowRedirects":"global","_type":"request"},{"_id":"req_ac402adaa67448d1b1759fa11242fcdc","parentId":"fld_5dd33b4bc38041d6820e9a61d2fb0a2f","modified":1681913023760,"created":1681903018591,"url":"localhost:3000/vendedor","name":"CADASTRAR","description":"","method":"POST","body":{"mimeType":"application/json","text":"\t{\n\t\t\"nome\": \"Carlinho ruindade pura\",\n\t\t\"matricula\": 1516\n\t}"},"parameters":[],"headers":[{"name":"Content-Type","value":"application/json"}],"authentication":{},"metaSortKey":-1681775214126,"isPrivate":false,"settingStoreCookies":true,"settingSendCookies":true,"settingDisableRenderRequestBody":false,"settingEncodeUrl":true,"settingRebuildPath":true,"settingFollowRedirects":"global","_type":"request"},{"_id":"req_c1a44f1c5221453186bca5ec2f1b0a1d","parentId":"fld_5dd33b4bc38041d6820e9a61d2fb0a2f","modified":1681913014647,"created":1681903018595,"url":"localhost:3000/alterarVendedor","name":"ALTERAR","description":"","method":"PUT","body":{"mimeType":"application/json","text":"\t{\n\t\t\"id\": 2,\n\t\t\"nome\": \"Carlao\",\n\t\t\"matricula\": 1516\n\t}"},"parameters":[],"headers":[{"name":"Content-Type","value":"application/json"}],"authentication":{},"metaSortKey":-1681753933997,"isPrivate":false,"settingStoreCookies":true,"settingSendCookies":true,"settingDisableRenderRequestBody":false,"settingEncodeUrl":true,"settingRebuildPath":true,"settingFollowRedirects":"global","_type":"request"},{"_id":"req_5a8ce3c3705b4683b4a1988b12ad1fb4","parentId":"fld_5dd33b4bc38041d6820e9a61d2fb0a2f","modified":1681910089018,"created":1681903018599,"url":"localhost:3000/excluirVendedor/1","name":"DELETAR","description":"","method":"DELETE","body":{},"parameters":[],"headers":[],"authentication":{},"metaSortKey":-1681743293932.5,"isPrivate":false,"settingStoreCookies":true,"settingSendCookies":true,"settingDisableRenderRequestBody":false,"settingEncodeUrl":true,"settingRebuildPath":true,"settingFollowRedirects":"global","_type":"request"},{"_id":"env_2c184f73358c09cd9916d2d767ce8a281e14e637","parentId":"wrk_c14a89b946ed439791c1ebeb36f744c1","modified":1681902842627,"created":1681902842627,"name":"Base Environment","data":{},"dataPropertyOrder":null,"color":null,"isPrivate":false,"metaSortKey":1681902842627,"_type":"environment"},{"_id":"jar_2c184f73358c09cd9916d2d767ce8a281e14e637","parentId":"wrk_c14a89b946ed439791c1ebeb36f744c1","modified":1681902842630,"created":1681902842630,"name":"Default Jar","cookies":[],"_type":"cookie_jar"},{"_id":"spc_4685bff1362a486eb6b58f03929fb61a","parentId":"wrk_c14a89b946ed439791c1ebeb36f744c1","modified":1681902842618,"created":1681902842618,"fileName":"Lojinha","contents":"","contentType":"yaml","_type":"api_spec"}]}